{
  "Profiles": [
    {
      "Name": "Dotfiles",
      "Guid": "9D734070-2D6B-47D9-BA7A-A36B87504C07",
      "Tags": ["dotfiles"],
      "Dynamic Profile Parent Name": "Default",
      "Normal Font": "JetBrainsMonoNerdFontComplete-Regular 13",
      "Non Ascii Font": "JetBrainsMonoNerdFontComplete-Regular 13",
      "Use Bright Bold": true,
      "Cursor Type": 2,
      "Use Italic Font": true,
      "Transparency": 0,
      "Blend": 0,
      "ASCII Anti Aliased": true,
      "Non-ASCII Anti Aliased": true,
      "Scrollback Lines": 100000,
      "Unlimited Scrollback": false,
      "Terminal Type": "xterm-256color"
    }
  ]
}
